[
  {
    "subreddit": "ChineseLanguage",
    "query": "resource",
    "title": "What are the best resources for learning Mandarin?",
    "permalink": "https://old.reddit.com/r/ChineseLanguage/comments/1td71bu/what_are_the_best_resources_for_learning_mandarin/",
    "created_utc": 1778783669,
    "created_at": "2026-05-14T18:34:29.000Z",
    "num_comments": 29,
    "author": "Emotional-Pop592",
    "score": 9
  },
  {
    "subreddit": "ChineseLanguage",
    "query": "app OR website pinyin hanzi",
    "title": "pinyin camera https://apps.apple.com/app/id6766483875",
    "permalink": "https://old.reddit.com/r/ChineseLanguage/comments/1tc1swl/pinyin_camera_httpsappsapplecomappid6766483875/",
    "created_utc": 1778683545,
    "created_at": "2026-05-13T14:45:45.000Z",
    "num_comments": 1,
    "author": "False-Potential1158",
    "score": 8
  },
  {
    "subreddit": "ChineseLanguage",
    "query": "\"learn chinese\" app",
    "title": "Any good cheap learning resources recommendations?",
    "permalink": "https://old.reddit.com/r/ChineseLanguage/comments/1sqcm92/any_good_cheap_learning_resources_recommendations/",
    "created_utc": 1776652273,
    "created_at": "2026-04-20T02:31:13.000Z",
    "num_comments": 7,
    "author": "kigukusuo",
    "score": 8
  },
  {
    "subreddit": "ChineseLanguage",
    "query": "\"learn chinese\" app",
    "title": "Are there any good free apps/websites to use for learning Chinese?",
    "permalink": "https://old.reddit.com/r/ChineseLanguage/comments/1sq06f2/are_there_any_good_free_appswebsites_to_use_for/",
    "created_utc": 1776621661,
    "created_at": "2026-04-19T18:01:01.000Z",
    "num_comments": 7,
    "author": "Strawby1_",
    "score": 8
  },
  {
    "subreddit": "ChineseLanguage",
    "query": "resource",
    "title": "Resources to learn Hakka",
    "permalink": "https://old.reddit.com/r/ChineseLanguage/comments/1te003v/resources_to_learn_hakka/",
    "created_utc": 1778859548,
    "created_at": "2026-05-15T15:39:08.000Z",
    "num_comments": 1,
    "author": "Loud_Set_8458",
    "score": 7
  },
  {
    "subreddit": "ChineseLanguage",
    "query": "resource",
    "title": "Resources of Romeo and Juliet in Chinese?",
    "permalink": "https://old.reddit.com/r/ChineseLanguage/comments/1ta8df2/resources_of_romeo_and_juliet_in_chinese/",
    "created_utc": 1778516849,
    "created_at": "2026-05-11T16:27:29.000Z",
    "num_comments": 3,
    "author": "Heidiuwuwuwu",
    "score": 7
  },
  {
    "subreddit": "ChineseLanguage",
    "query": "\"learn chinese\" app",
    "title": "Best app for learning",
    "permalink": "https://old.reddit.com/r/ChineseLanguage/comments/1tbwk45/best_app_for_learning/",
    "created_utc": 1778670976,
    "created_at": "2026-05-13T11:16:16.000Z",
    "num_comments": 9,
    "author": "misunni",
    "score": 6
  },
  {
    "subreddit": "ChineseLanguage",
    "query": "\"learn chinese\" app",
    "title": "Anyone else do this to learn chinese?",
    "permalink": "https://old.reddit.com/r/ChineseLanguage/comments/1tbvw53/anyone_else_do_this_to_learn_chinese/",
    "created_utc": 1778669002,
    "created_at": "2026-05-13T10:43:22.000Z",
    "num_comments": 4,
    "author": "Atee_Vicky",
    "score": 6
  },
  {
    "subreddit": "ChineseLanguage",
    "query": "\"learn chinese\" app",
    "title": "Which apps are worth the money? And what are must know YouTube channels?",
    "permalink": "https://old.reddit.com/r/ChineseLanguage/comments/1t0q6do/which_apps_are_worth_the_money_and_what_are_must/",
    "created_utc": 1777633293,
    "created_at": "2026-05-01T11:01:33.000Z",
    "num_comments": 20,
    "author": "DankTyl",
    "score": 6
  },
  {
    "subreddit": "ChineseLanguage",
    "query": "flashcard app",
    "title": "I’m new here and I’ve created a free app to learn Chinese. What do you think?",
    "permalink": "https://old.reddit.com/r/ChineseLanguage/comments/1srqs12/im_new_here_and_ive_created_a_free_app_to_learn/",
    "created_utc": 1776784754,
    "created_at": "2026-04-21T15:19:14.000Z",
    "num_comments": 3,
    "author": "Own-Artichoke-1578",
    "score": 6
  },
  {
    "subreddit": "ChineseLanguage",
    "query": "\"learn chinese\" app",
    "title": "where to start leaning chinese",
    "permalink": "https://old.reddit.com/r/ChineseLanguage/comments/1tdv5e1/where_to_start_leaning_chinese/",
    "created_utc": 1778848758,
    "created_at": "2026-05-15T12:39:18.000Z",
    "num_comments": 1,
    "author": "hehe2227",
    "score": 5
  },
  {
    "subreddit": "ChineseLanguage",
    "query": "resource",
    "title": "Web based Chinese language simulator to rehearse specific real world tasks",
    "permalink": "https://old.reddit.com/r/ChineseLanguage/comments/1tc8k3u/web_based_chinese_language_simulator_to_rehearse/",
    "created_utc": 1778697277,
    "created_at": "2026-05-13T18:34:37.000Z",
    "num_comments": 0,
    "author": "110_percent_wrong",
    "score": 5
  },
  {
    "subreddit": "ChineseLanguage",
    "query": "\"learn chinese\" app",
    "title": "I want to design an app to learn chinese cantonese",
    "permalink": "https://old.reddit.com/r/ChineseLanguage/comments/1sxulkq/i_want_to_design_an_app_to_learn_chinese_cantonese/",
    "created_utc": 1777362191,
    "created_at": "2026-04-28T07:43:11.000Z",
    "num_comments": 0,
    "author": "Some-Spite-5825",
    "score": 5
  },
  {
    "subreddit": "ChineseLanguage",
    "query": "\"learn chinese\" app",
    "title": "Learning hanzi with Hellochinese",
    "permalink": "https://old.reddit.com/r/ChineseLanguage/comments/1t676kp/learning_hanzi_with_hellochinese/",
    "created_utc": 1778151805,
    "created_at": "2026-05-07T11:03:25.000Z",
    "num_comments": 5,
    "author": "DankTyl",
    "score": 4
  },
  {
    "subreddit": "ChineseLanguage",
    "query": "app OR website pinyin hanzi",
    "title": "Looking for a simple Anki deck for extremely basic Chinese for travel phrases (pinyin & audio)",
    "permalink": "https://old.reddit.com/r/ChineseLanguage/comments/1t3vcre/looking_for_a_simple_anki_deck_for_extremely/",
    "created_utc": 1777930134,
    "created_at": "2026-05-04T21:28:54.000Z",
    "num_comments": 3,
    "author": "CallMeGolem",
    "score": 4
  },
  {
    "subreddit": "ChineseLanguage",
    "query": "\"learn chinese\" app",
    "title": "What is the best way to learn Chinese language?",
    "permalink": "https://old.reddit.com/r/ChineseLanguage/comments/1t27gtb/what_is_the_best_way_to_learn_chinese_language/",
    "created_utc": 1777770877,
    "created_at": "2026-05-03T01:14:37.000Z",
    "num_comments": 4,
    "author": "ExistentialBananaz",
    "score": 4
  },
  {
    "subreddit": "ChineseLanguage",
    "query": "\"learn chinese\" app",
    "title": "Tips??",
    "permalink": "https://old.reddit.com/r/ChineseLanguage/comments/1t23d55/tips/",
    "created_utc": 1777759773,
    "created_at": "2026-05-02T22:09:33.000Z",
    "num_comments": 2,
    "author": "Local-Corner7885",
    "score": 4
  },
  {
    "subreddit": "ChineseLanguage",
    "query": "\"learn chinese\" app",
    "title": "I'm totally new to learning Chinese but I'm spanish native speaker learning Japanese. How should I start?",
    "permalink": "https://old.reddit.com/r/ChineseLanguage/comments/1sr9voe/im_totally_new_to_learning_chinese_but_im_spanish/",
    "created_utc": 1776736020,
    "created_at": "2026-04-21T01:47:00.000Z",
    "num_comments": 2,
    "author": "manutre00",
    "score": 4
  },
  {
    "subreddit": "ChineseLanguage",
    "query": "flashcard app",
    "title": "Some (seemingly) less known resources I find helpful",
    "permalink": "https://old.reddit.com/r/ChineseLanguage/comments/1sl92a8/some_seemingly_less_known_resources_i_find_helpful/",
    "created_utc": 1776174060,
    "created_at": "2026-04-14T13:41:00.000Z",
    "num_comments": 2,
    "author": "NordSol",
    "score": 4
  }
]
