[
  {
    "subreddit": "ChineseLanguage",
    "query": "resource",
    "title": "For those moving to the new HSK course, are you finding the lack of resources refreshing like me?",
    "permalink": "https://old.reddit.com/r/ChineseLanguage/comments/1rt5l69/for_those_moving_to_the_new_hsk_course_are_you/",
    "created_utc": 1773450109,
    "created_at": "2026-03-14T01:01:49.000Z",
    "num_comments": 12,
    "author": "Significant_Corner41",
    "score": 9
  },
  {
    "subreddit": "ChineseLanguage",
    "query": "\"learn chinese\" app",
    "title": "What is the best app to learn Mandarin ?",
    "permalink": "https://old.reddit.com/r/ChineseLanguage/comments/1rql3xs/what_is_the_best_app_to_learn_mandarin/",
    "created_utc": 1773206691,
    "created_at": "2026-03-11T05:24:51.000Z",
    "num_comments": 14,
    "author": "Alarmed_Occasion7375",
    "score": 7
  },
  {
    "subreddit": "ChineseLanguage",
    "query": "\"learn chinese\" app",
    "title": "Learning Chinese as a new language - recommend any language apps",
    "permalink": "https://old.reddit.com/r/ChineseLanguage/comments/1rqachb/learning_chinese_as_a_new_language_recommend_any/",
    "created_utc": 1773178628,
    "created_at": "2026-03-10T21:37:08.000Z",
    "num_comments": 12,
    "author": "sagemode888",
    "score": 7
  },
  {
    "subreddit": "ChineseLanguage",
    "query": "flashcard app",
    "title": "TOFU Learn alternative",
    "permalink": "https://old.reddit.com/r/ChineseLanguage/comments/1rtjae8/tofu_learn_alternative/",
    "created_utc": 1773494479,
    "created_at": "2026-03-14T13:21:19.000Z",
    "num_comments": 0,
    "author": "sigmaballs6969",
    "score": 6
  },
  {
    "subreddit": "ChineseLanguage",
    "query": "resource",
    "title": "Learning resource from the wild #2",
    "permalink": "https://old.reddit.com/r/ChineseLanguage/comments/1rso5xj/learning_resource_from_the_wild_2/",
    "created_utc": 1773410537,
    "created_at": "2026-03-13T14:02:17.000Z",
    "num_comments": 1,
    "author": "MPforNarnia",
    "score": 6
  },
  {
    "subreddit": "ChineseLanguage",
    "query": "resource",
    "title": "Learning resources tips",
    "permalink": "https://old.reddit.com/r/ChineseLanguage/comments/1rscy0h/learning_resources_tips/",
    "created_utc": 1773373975,
    "created_at": "2026-03-13T03:52:55.000Z",
    "num_comments": 8,
    "author": "kirso",
    "score": 6
  },
  {
    "subreddit": "ChineseLanguage",
    "query": "\"learn chinese\" app",
    "title": "Learning Chinese characters in food apps to avoid menu confusion",
    "permalink": "https://old.reddit.com/r/ChineseLanguage/comments/1rsarvp/learning_chinese_characters_in_food_apps_to_avoid/",
    "created_utc": 1773367829,
    "created_at": "2026-03-13T02:10:29.000Z",
    "num_comments": 18,
    "author": "songdoremi",
    "score": 6
  },
  {
    "subreddit": "ChineseLanguage",
    "query": "\"learn chinese\" app",
    "title": "How to remove HSK 3.0 flashcards from Pleco?",
    "permalink": "https://old.reddit.com/r/ChineseLanguage/comments/1re9z8d/how_to_remove_hsk_30_flashcards_from_pleco/",
    "created_utc": 1772016374,
    "created_at": "2026-02-25T10:46:14.000Z",
    "num_comments": 10,
    "author": "Shyam_Lama",
    "score": 6
  },
  {
    "subreddit": "ChineseLanguage",
    "query": "\"learn chinese\" app",
    "title": "Best app for conversational Mandarin?",
    "permalink": "https://old.reddit.com/r/ChineseLanguage/comments/1r6cjlc/best_app_for_conversational_mandarin/",
    "created_utc": 1771255613,
    "created_at": "2026-02-16T15:26:53.000Z",
    "num_comments": 13,
    "author": "Adventurous-Claim334",
    "score": 6
  },
  {
    "subreddit": "ChineseLanguage",
    "query": "app OR website pinyin hanzi",
    "title": "Hanzi on back or front of flashcards",
    "permalink": "https://old.reddit.com/r/ChineseLanguage/comments/1r67cfi/hanzi_on_back_or_front_of_flashcards/",
    "created_utc": 1771241824,
    "created_at": "2026-02-16T11:37:04.000Z",
    "num_comments": 2,
    "author": "Salitur",
    "score": 6
  },
  {
    "subreddit": "ChineseLanguage",
    "query": "resource",
    "title": "I’m taking the HSK 3 exam this weekend. Any last-minute tips from people who passed?",
    "permalink": "https://old.reddit.com/r/ChineseLanguage/comments/1rqxi0l/im_taking_the_hsk_3_exam_this_weekend_any/",
    "created_utc": 1773244295,
    "created_at": "2026-03-11T15:51:35.000Z",
    "num_comments": 24,
    "author": "s632061",
    "score": 5
  },
  {
    "subreddit": "ChineseLanguage",
    "query": "resource",
    "title": "Resources to Self-Learn Reading and Writing Chinese (Mandarin and Cantonese) in 3-6 months for the Workplace",
    "permalink": "https://old.reddit.com/r/ChineseLanguage/comments/1rouplk/resources_to_selflearn_reading_and_writing/",
    "created_utc": 1773045276,
    "created_at": "2026-03-09T08:34:36.000Z",
    "num_comments": 7,
    "author": "RHYKQO",
    "score": 5
  },
  {
    "subreddit": "ChineseLanguage",
    "query": "resource",
    "title": "Learning resources from the wild #1",
    "permalink": "https://old.reddit.com/r/ChineseLanguage/comments/1rntf44/learning_resources_from_the_wild_1/",
    "created_utc": 1772938850,
    "created_at": "2026-03-08T03:00:50.000Z",
    "num_comments": 18,
    "author": "MPforNarnia",
    "score": 5
  },
  {
    "subreddit": "ChineseLanguage",
    "query": "app OR website pinyin hanzi",
    "title": "Total Beginner in need of help with sentences.",
    "permalink": "https://old.reddit.com/r/ChineseLanguage/comments/1rrzo0i/total_beginner_in_need_of_help_with_sentences/",
    "created_utc": 1773341869,
    "created_at": "2026-03-12T18:57:49.000Z",
    "num_comments": 5,
    "author": "cloggednueron",
    "score": 4
  },
  {
    "subreddit": "ChineseLanguage",
    "query": "\"learn chinese\" app",
    "title": "Best Chinese language apps for advanced studying",
    "permalink": "https://old.reddit.com/r/ChineseLanguage/comments/1rmep1u/best_chinese_language_apps_for_advanced_studying/",
    "created_utc": 1772805511,
    "created_at": "2026-03-06T13:58:31.000Z",
    "num_comments": 6,
    "author": "AdApprehensive8858",
    "score": 4
  },
  {
    "subreddit": "ChineseLanguage",
    "query": "\"learn chinese\" app",
    "title": "What is your favorite language learning app?",
    "permalink": "https://old.reddit.com/r/ChineseLanguage/comments/1rffoad/what_is_your_favorite_language_learning_app/",
    "created_utc": 1772125253,
    "created_at": "2026-02-26T17:00:53.000Z",
    "num_comments": 38,
    "author": "Mysterious_Cash5090",
    "score": 4
  },
  {
    "subreddit": "ChineseLanguage",
    "query": "\"learn chinese\" app",
    "title": "Looking for 12 testers for a classical Chinese poetry puzzle app (Google Play closed test)",
    "permalink": "https://old.reddit.com/r/ChineseLanguage/comments/1rbk5i6/looking_for_12_testers_for_a_classical_chinese/",
    "created_utc": 1771761796,
    "created_at": "2026-02-22T12:03:16.000Z",
    "num_comments": 3,
    "author": "ggzy12345",
    "score": 4
  },
  {
    "subreddit": "ChineseLanguage",
    "query": "\"learn chinese\" app",
    "title": "HelloChinese vs Laoshi App",
    "permalink": "https://old.reddit.com/r/ChineseLanguage/comments/1r4wglp/hellochinese_vs_laoshi_app/",
    "created_utc": 1771104524,
    "created_at": "2026-02-14T21:28:44.000Z",
    "num_comments": 5,
    "author": "Jolly_Fall_8369",
    "score": 4
  },
  {
    "subreddit": "ChineseLanguage",
    "query": "app OR website pinyin hanzi",
    "title": "Studying relationships between hanzi",
    "permalink": "https://old.reddit.com/r/ChineseLanguage/comments/1r4cs1r/studying_relationships_between_hanzi/",
    "created_utc": 1771048526,
    "created_at": "2026-02-14T05:55:26.000Z",
    "num_comments": 24,
    "author": "jrmxrf",
    "score": 4
  },
  {
    "subreddit": "ChineseLanguage",
    "query": "\"learn chinese\" app",
    "title": "podcast app",
    "permalink": "https://old.reddit.com/r/ChineseLanguage/comments/1r26ptj/podcast_app/",
    "created_utc": 1770837477,
    "created_at": "2026-02-11T19:17:57.000Z",
    "num_comments": 4,
    "author": "leemeanhyuk",
    "score": 4
  }
]
