[
  {
    "subreddit": "ChineseLanguage",
    "query": "app OR website pinyin hanzi",
    "title": "I'm looking for a font for chinese pinyin and hanzi",
    "permalink": "https://old.reddit.com/r/ChineseLanguage/comments/1rzw5qg/im_looking_for_a_font_for_chinese_pinyin_and_hanzi/",
    "created_utc": 1774111316,
    "created_at": "2026-03-21T16:41:56.000Z",
    "num_comments": 4,
    "author": "Imaginary_Stomach139",
    "score": 9
  },
  {
    "subreddit": "ChineseLanguage",
    "query": "resource",
    "title": "Amazing resource",
    "permalink": "https://old.reddit.com/r/ChineseLanguage/comments/1s0adg9/amazing_resource/",
    "created_utc": 1774147656,
    "created_at": "2026-03-22T02:47:36.000Z",
    "num_comments": 5,
    "author": "Dezn425",
    "score": 7
  },
  {
    "subreddit": "ChineseLanguage",
    "query": "resource",
    "title": "beginner resources",
    "permalink": "https://old.reddit.com/r/ChineseLanguage/comments/1rzl8jy/beginner_resources/",
    "created_utc": 1774077800,
    "created_at": "2026-03-21T07:23:20.000Z",
    "num_comments": 6,
    "author": "Realistic_Level7375",
    "score": 6
  },
  {
    "subreddit": "ChineseLanguage",
    "query": "\"learn chinese\" app",
    "title": "What is the best app to learn Mandarin ?",
    "permalink": "https://old.reddit.com/r/ChineseLanguage/comments/1rql3xs/what_is_the_best_app_to_learn_mandarin/",
    "created_utc": 1773206691,
    "created_at": "2026-03-11T05:24:51.000Z",
    "num_comments": 14,
    "author": "Alarmed_Occasion7375",
    "score": 6
  },
  {
    "subreddit": "ChineseLanguage",
    "query": "\"learn chinese\" app",
    "title": "Learning Chinese as a new language - recommend any language apps",
    "permalink": "https://old.reddit.com/r/ChineseLanguage/comments/1rqachb/learning_chinese_as_a_new_language_recommend_any/",
    "created_utc": 1773178628,
    "created_at": "2026-03-10T21:37:08.000Z",
    "num_comments": 13,
    "author": "sagemode888",
    "score": 6
  },
  {
    "subreddit": "ChineseLanguage",
    "query": "\"learn chinese\" app",
    "title": "How to remove HSK 3.0 flashcards from Pleco?",
    "permalink": "https://old.reddit.com/r/ChineseLanguage/comments/1re9z8d/how_to_remove_hsk_30_flashcards_from_pleco/",
    "created_utc": 1772016374,
    "created_at": "2026-02-25T10:46:14.000Z",
    "num_comments": 10,
    "author": "Shyam_Lama",
    "score": 6
  },
  {
    "subreddit": "ChineseLanguage",
    "query": "\"learn chinese\" app",
    "title": "🚀 New Drop: Inside China’s Reusable Rocket Race",
    "permalink": "https://old.reddit.com/r/ChineseLanguage/comments/1ry205o/new_drop_inside_chinas_reusable_rocket_race/",
    "created_utc": 1773930708,
    "created_at": "2026-03-19T14:31:48.000Z",
    "num_comments": 0,
    "author": "eeasonloo",
    "score": 5
  },
  {
    "subreddit": "ChineseLanguage",
    "query": "resource",
    "title": "anywhere that i can learn specifically vocabulary?",
    "permalink": "https://old.reddit.com/r/ChineseLanguage/comments/1ruvdtx/anywhere_that_i_can_learn_specifically_vocabulary/",
    "created_utc": 1773622641,
    "created_at": "2026-03-16T00:57:21.000Z",
    "num_comments": 2,
    "author": "SpecialNo7698",
    "score": 5
  },
  {
    "subreddit": "ChineseLanguage",
    "query": "resource",
    "title": "HSK 3 study: Is it enough just to use DuChinese and Skritter?",
    "permalink": "https://old.reddit.com/r/ChineseLanguage/comments/1rudhsy/hsk_3_study_is_it_enough_just_to_use_duchinese/",
    "created_utc": 1773579778,
    "created_at": "2026-03-15T13:02:58.000Z",
    "num_comments": 10,
    "author": "Hungry-Cricket-9872",
    "score": 5
  },
  {
    "subreddit": "ChineseLanguage",
    "query": "app OR website pinyin hanzi",
    "title": "beginner at HSK 1,need help",
    "permalink": "https://old.reddit.com/r/ChineseLanguage/comments/1rz1210/beginner_at_hsk_1need_help/",
    "created_utc": 1774024269,
    "created_at": "2026-03-20T16:31:09.000Z",
    "num_comments": 15,
    "author": "Birdi_lover",
    "score": 4
  },
  {
    "subreddit": "ChineseLanguage",
    "query": "app OR website pinyin hanzi",
    "title": "Are there any “default” word swaps native speakers use that learners miss? (HSK 3 to HSK 4)",
    "permalink": "https://old.reddit.com/r/ChineseLanguage/comments/1rye3ld/are_there_any_default_word_swaps_native_speakers/",
    "created_utc": 1773958208,
    "created_at": "2026-03-19T22:10:08.000Z",
    "num_comments": 41,
    "author": "s632061",
    "score": 4
  },
  {
    "subreddit": "ChineseLanguage",
    "query": "\"learn chinese\" app",
    "title": "Wanting to start learning Chinese!",
    "permalink": "https://old.reddit.com/r/ChineseLanguage/comments/1ry1nji/wanting_to_start_learning_chinese/",
    "created_utc": 1773929921,
    "created_at": "2026-03-19T14:18:41.000Z",
    "num_comments": 7,
    "author": "Jealous-Butterfly205",
    "score": 4
  },
  {
    "subreddit": "ChineseLanguage",
    "query": "resource",
    "title": "Self study",
    "permalink": "https://old.reddit.com/r/ChineseLanguage/comments/1ruemrq/self_study/",
    "created_utc": 1773582853,
    "created_at": "2026-03-15T13:54:13.000Z",
    "num_comments": 0,
    "author": "Due-Lavishness9483",
    "score": 4
  },
  {
    "subreddit": "ChineseLanguage",
    "query": "\"learn chinese\" app",
    "title": "Learning Chinese characters in food apps to avoid menu confusion",
    "permalink": "https://old.reddit.com/r/ChineseLanguage/comments/1rsarvp/learning_chinese_characters_in_food_apps_to_avoid/",
    "created_utc": 1773367829,
    "created_at": "2026-03-13T02:10:29.000Z",
    "num_comments": 20,
    "author": "songdoremi",
    "score": 4
  },
  {
    "subreddit": "ChineseLanguage",
    "query": "\"learn chinese\" app",
    "title": "Best Chinese language apps for advanced studying",
    "permalink": "https://old.reddit.com/r/ChineseLanguage/comments/1rmep1u/best_chinese_language_apps_for_advanced_studying/",
    "created_utc": 1772805511,
    "created_at": "2026-03-06T13:58:31.000Z",
    "num_comments": 13,
    "author": "AdApprehensive8858",
    "score": 4
  },
  {
    "subreddit": "ChineseLanguage",
    "query": "\"learn chinese\" app",
    "title": "What is your favorite language learning app?",
    "permalink": "https://old.reddit.com/r/ChineseLanguage/comments/1rffoad/what_is_your_favorite_language_learning_app/",
    "created_utc": 1772125253,
    "created_at": "2026-02-26T17:00:53.000Z",
    "num_comments": 38,
    "author": "Mysterious_Cash5090",
    "score": 4
  },
  {
    "subreddit": "ChineseLanguage",
    "query": "\"learn chinese\" app",
    "title": "Looking for 12 testers for a classical Chinese poetry puzzle app (Google Play closed test)",
    "permalink": "https://old.reddit.com/r/ChineseLanguage/comments/1rbk5i6/looking_for_12_testers_for_a_classical_chinese/",
    "created_utc": 1771761796,
    "created_at": "2026-02-22T12:03:16.000Z",
    "num_comments": 3,
    "author": "ggzy12345",
    "score": 4
  }
]
